[
  {
    "plterm": "niebieski",
    "roterm": "albastru",
    "dist": 15.530379294690741,
    "plterm_refined": "niebieski",
    "roterm_refined": "albastru"
  },
  {
    "plterm": "niebieski",
    "roterm": "verde",
    "dist": 146.555244555156,
    "plterm_refined": "niebieski",
    "roterm_refined": "verde"
  },
  {
    "plterm": "niebieski",
    "roterm": "roz",
    "dist": 81.01127566732885,
    "plterm_refined": "niebieski",
    "roterm_refined": "roz"
  },
  {
    "plterm": "niebieski",
    "roterm": "mov",
    "dist": 67.21963852086294,
    "plterm_refined": "niebieski",
    "roterm_refined": "mov"
  },
  {
    "plterm": "zielony",
    "roterm": "albastru",
    "dist": 152.95705894371824,
    "plterm_refined": "zielony",
    "roterm_refined": "albastru"
  },
  {
    "plterm": "zielony",
    "roterm": "verde",
    "dist": 11.740271862682581,
    "plterm_refined": "zielony",
    "roterm_refined": "verde"
  },
  {
    "plterm": "zielony",
    "roterm": "roz",
    "dist": 160.414078810269,
    "plterm_refined": "zielony",
    "roterm_refined": "roz"
  },
  {
    "plterm": "zielony",
    "roterm": "mov",
    "dist": 183.87686228081338,
    "plterm_refined": "zielony",
    "roterm_refined": "mov"
  },
  {
    "plterm": "fioletowy",
    "roterm": "albastru",
    "dist": 49.684162409157615,
    "plterm_refined": "fioletowy",
    "roterm_refined": "albastru"
  },
  {
    "plterm": "fioletowy",
    "roterm": "verde",
    "dist": 184.6098080530412,
    "plterm_refined": "fioletowy",
    "roterm_refined": "verde"
  },
  {
    "plterm": "fioletowy",
    "roterm": "roz",
    "dist": 45.556308120987076,
    "plterm_refined": "fioletowy",
    "roterm_refined": "roz"
  },
  {
    "plterm": "fioletowy",
    "roterm": "mov",
    "dist": 15.23296415525189,
    "plterm_refined": "fioletowy",
    "roterm_refined": "mov"
  },
  {
    "plterm": "rozowy",
    "roterm": "albastru",
    "dist": 78.89727017540956,
    "plterm_refined": "rozowy",
    "roterm_refined": "albastru"
  },
  {
    "plterm": "rozowy",
    "roterm": "verde",
    "dist": 165.91191649270226,
    "plterm_refined": "rozowy",
    "roterm_refined": "verde"
  },
  {
    "plterm": "rozowy",
    "roterm": "roz",
    "dist": 8.171428928687181,
    "plterm_refined": "rozowy",
    "roterm_refined": "roz"
  },
  {
    "plterm": "rozowy",
    "roterm": "mov",
    "dist": 46.4243176118507,
    "plterm_refined": "rozowy",
    "roterm_refined": "mov"
  },
  {
    "plterm": "pomaranczowy",
    "roterm": "albastru",
    "dist": 142.53320910082599,
    "plterm_refined": "pomaranczowy",
    "roterm_refined": "albastru"
  },
  {
    "plterm": "pomaranczowy",
    "roterm": "verde",
    "dist": 109.25012713758049,
    "plterm_refined": "pomaranczowy",
    "roterm_refined": "verde"
  },
  {
    "plterm": "pomaranczowy",
    "roterm": "roz",
    "dist": 99.08775750027273,
    "plterm_refined": "pomaranczowy",
    "roterm_refined": "roz"
  },
  {
    "plterm": "pomaranczowy",
    "roterm": "mov",
    "dist": 138.2126307679289,
    "plterm_refined": "pomaranczowy",
    "roterm_refined": "mov"
  },
  {
    "plterm": "czerwony",
    "roterm": "albastru",
    "dist": 131.75319644020203,
    "plterm_refined": "czerwony",
    "roterm_refined": "albastru"
  },
  {
    "plterm": "czerwony",
    "roterm": "verde",
    "dist": 145.6780368113303,
    "plterm_refined": "czerwony",
    "roterm_refined": "verde"
  },
  {
    "plterm": "czerwony",
    "roterm": "roz",
    "dist": 69.52074225887317,
    "plterm_refined": "czerwony",
    "roterm_refined": "roz"
  },
  {
    "plterm": "czerwony",
    "roterm": "mov",
    "dist": 108.42398960248528,
    "plterm_refined": "czerwony",
    "roterm_refined": "mov"
  },
  {
    "plterm": "zołty",
    "roterm": "albastru",
    "dist": 161.8402746245685,
    "plterm_refined": "zołty",
    "roterm_refined": "albastru"
  },
  {
    "plterm": "zołty",
    "roterm": "verde",
    "dist": 60.74291106815108,
    "plterm_refined": "zołty",
    "roterm_refined": "verde"
  },
  {
    "plterm": "zołty",
    "roterm": "roz",
    "dist": 142.00491186086822,
    "plterm_refined": "zołty",
    "roterm_refined": "roz"
  },
  {
    "plterm": "zołty",
    "roterm": "mov",
    "dist": 175.76499076997752,
    "plterm_refined": "zołty",
    "roterm_refined": "mov"
  },
  {
    "plterm": "turkusowy",
    "roterm": "albastru",
    "dist": 102.31078929053976,
    "plterm_refined": "turkusowy",
    "roterm_refined": "albastru"
  },
  {
    "plterm": "turkusowy",
    "roterm": "verde",
    "dist": 66.57043511801075,
    "plterm_refined": "turkusowy",
    "roterm_refined": "verde"
  },
  {
    "plterm": "turkusowy",
    "roterm": "roz",
    "dist": 131.62415945809707,
    "plterm_refined": "turkusowy",
    "roterm_refined": "roz"
  },
  {
    "plterm": "turkusowy",
    "roterm": "mov",
    "dist": 144.4526863542022,
    "plterm_refined": "turkusowy",
    "roterm_refined": "mov"
  },
  {
    "plterm": "granatowy",
    "roterm": "albastru",
    "dist": 31.52196307903322,
    "plterm_refined": "granatowy",
    "roterm_refined": "albastru"
  },
  {
    "plterm": "granatowy",
    "roterm": "verde",
    "dist": 174.8142269077664,
    "plterm_refined": "granatowy",
    "roterm_refined": "verde"
  },
  {
    "plterm": "granatowy",
    "roterm": "roz",
    "dist": 70.34276034532651,
    "plterm_refined": "granatowy",
    "roterm_refined": "roz"
  },
  {
    "plterm": "granatowy",
    "roterm": "mov",
    "dist": 44.46553972077292,
    "plterm_refined": "granatowy",
    "roterm_refined": "mov"
  },
  {
    "plterm": "brazowy",
    "roterm": "albastru",
    "dist": 104.14657908601926,
    "plterm_refined": "brazowy",
    "roterm_refined": "albastru"
  },
  {
    "plterm": "brazowy",
    "roterm": "verde",
    "dist": 101.44290404844394,
    "plterm_refined": "brazowy",
    "roterm_refined": "verde"
  },
  {
    "plterm": "brazowy",
    "roterm": "roz",
    "dist": 80.799941631814,
    "plterm_refined": "brazowy",
    "roterm_refined": "roz"
  },
  {
    "plterm": "brazowy",
    "roterm": "mov",
    "dist": 109.16946748829592,
    "plterm_refined": "brazowy",
    "roterm_refined": "mov"
  },
  {
    "plterm": "jasnozielony",
    "roterm": "albastru",
    "dist": 162.12392196077622,
    "plterm_refined": "jasnozielony",
    "roterm_refined": "albastru"
  },
  {
    "plterm": "jasnozielony",
    "roterm": "verde",
    "dist": 18.023892740229314,
    "plterm_refined": "jasnozielony",
    "roterm_refined": "verde"
  },
  {
    "plterm": "jasnozielony",
    "roterm": "roz",
    "dist": 163.9391835645855,
    "plterm_refined": "jasnozielony",
    "roterm_refined": "roz"
  },
  {
    "plterm": "jasnozielony",
    "roterm": "mov",
    "dist": 190.2929608387252,
    "plterm_refined": "jasnozielony",
    "roterm_refined": "mov"
  },
  {
    "plterm": "seledynowy",
    "roterm": "albastru",
    "dist": 136.04769717871952,
    "plterm_refined": "seledynowy",
    "roterm_refined": "albastru"
  },
  {
    "plterm": "seledynowy",
    "roterm": "verde",
    "dist": 29.058297932196293,
    "plterm_refined": "seledynowy",
    "roterm_refined": "verde"
  },
  {
    "plterm": "seledynowy",
    "roterm": "roz",
    "dist": 148.32864141924463,
    "plterm_refined": "seledynowy",
    "roterm_refined": "roz"
  },
  {
    "plterm": "seledynowy",
    "roterm": "mov",
    "dist": 169.4250241550456,
    "plterm_refined": "seledynowy",
    "roterm_refined": "mov"
  },
  {
    "plterm": "szary",
    "roterm": "albastru",
    "dist": 78.38786742360818,
    "plterm_refined": "szary",
    "roterm_refined": "albastru"
  },
  {
    "plterm": "szary",
    "roterm": "verde",
    "dist": 94.13005955436478,
    "plterm_refined": "szary",
    "roterm_refined": "verde"
  },
  {
    "plterm": "szary",
    "roterm": "roz",
    "dist": 88.43038800940079,
    "plterm_refined": "szary",
    "roterm_refined": "roz"
  },
  {
    "plterm": "szary",
    "roterm": "mov",
    "dist": 104.34497175422123,
    "plterm_refined": "szary",
    "roterm_refined": "mov"
  },
  {
    "plterm": "ciemnozielony",
    "roterm": "albastru",
    "dist": 108.92851882297809,
    "plterm_refined": "ciemnozielony",
    "roterm_refined": "albastru"
  },
  {
    "plterm": "ciemnozielony",
    "roterm": "verde",
    "dist": 72.5347471865086,
    "plterm_refined": "ciemnozielony",
    "roterm_refined": "verde"
  },
  {
    "plterm": "ciemnozielony",
    "roterm": "roz",
    "dist": 120.3235065614843,
    "plterm_refined": "ciemnozielony",
    "roterm_refined": "roz"
  },
  {
    "plterm": "ciemnozielony",
    "roterm": "mov",
    "dist": 137.21369499493912,
    "plterm_refined": "ciemnozielony",
    "roterm_refined": "mov"
  },
  {
    "plterm": "czarny",
    "roterm": "albastru",
    "dist": 89.31360591728341,
    "plterm_refined": "czarny",
    "roterm_refined": "albastru"
  },
  {
    "plterm": "czarny",
    "roterm": "verde",
    "dist": 122.66136364520887,
    "plterm_refined": "czarny",
    "roterm_refined": "verde"
  },
  {
    "plterm": "czarny",
    "roterm": "roz",
    "dist": 91.821210206721,
    "plterm_refined": "czarny",
    "roterm_refined": "roz"
  },
  {
    "plterm": "czarny",
    "roterm": "mov",
    "dist": 102.4681565089926,
    "plterm_refined": "czarny",
    "roterm_refined": "mov"
  },
  {
    "plterm": "bordowy",
    "roterm": "albastru",
    "dist": 100.76422779642881,
    "plterm_refined": "bordowy",
    "roterm_refined": "albastru"
  },
  {
    "plterm": "bordowy",
    "roterm": "verde",
    "dist": 128.04802835157776,
    "plterm_refined": "bordowy",
    "roterm_refined": "verde"
  },
  {
    "plterm": "bordowy",
    "roterm": "roz",
    "dist": 61.82613375277391,
    "plterm_refined": "bordowy",
    "roterm_refined": "roz"
  },
  {
    "plterm": "bordowy",
    "roterm": "mov",
    "dist": 91.70488623468691,
    "plterm_refined": "bordowy",
    "roterm_refined": "mov"
  }
]