[
  {
    "ptterm": "azul", 
    "dist": 0.8528768941495621, 
    "enterm": "blue"
  }, 
  {
    "ptterm": "verde", 
    "dist": 15.31558518336572, 
    "enterm": "blue"
  }, 
  {
    "ptterm": "azul", 
    "dist": 13.214970539920573, 
    "enterm": "green"
  }, 
  {
    "ptterm": "verde", 
    "dist": 2.2997717912436975, 
    "enterm": "green"
  }, 
  {
    "ptterm": "azul", 
    "dist": 5.627025464112582, 
    "enterm": "purple"
  }, 
  {
    "ptterm": "verde", 
    "dist": 17.669076524449682, 
    "enterm": "purple"
  }, 
  {
    "ptterm": "azul", 
    "dist": 8.573020266754243, 
    "enterm": "pink"
  }, 
  {
    "ptterm": "verde", 
    "dist": 15.619063297743155, 
    "enterm": "pink"
  }, 
  {
    "ptterm": "azul", 
    "dist": 13.876572373968074, 
    "enterm": "red"
  }, 
  {
    "ptterm": "verde", 
    "dist": 14.253231688698621, 
    "enterm": "red"
  }, 
  {
    "ptterm": "azul", 
    "dist": 14.418145668472718, 
    "enterm": "orange"
  }, 
  {
    "ptterm": "verde", 
    "dist": 10.730837217118355, 
    "enterm": "orange"
  }, 
  {
    "ptterm": "azul", 
    "dist": 15.743476250806875, 
    "enterm": "yellow"
  }, 
  {
    "ptterm": "verde", 
    "dist": 5.923028517118699, 
    "enterm": "yellow"
  }, 
  {
    "ptterm": "azul", 
    "dist": 8.442649420230763, 
    "enterm": "magenta"
  }, 
  {
    "ptterm": "verde", 
    "dist": 17.057581846566066, 
    "enterm": "magenta"
  }, 
  {
    "ptterm": "azul", 
    "dist": 10.621914936929535, 
    "enterm": "brown"
  }, 
  {
    "ptterm": "verde", 
    "dist": 9.769785382978945, 
    "enterm": "brown"
  }, 
  {
    "ptterm": "azul", 
    "dist": 4.823978198141667, 
    "enterm": "lightblue"
  }, 
  {
    "ptterm": "verde", 
    "dist": 10.680950579227463, 
    "enterm": "lightblue"
  }, 
  {
    "ptterm": "azul", 
    "dist": 15.808910684622333, 
    "enterm": "limegreen"
  }, 
  {
    "ptterm": "verde", 
    "dist": 1.4953093022284014, 
    "enterm": "limegreen"
  }, 
  {
    "ptterm": "azul", 
    "dist": 8.4773009330862, 
    "enterm": "teal"
  }, 
  {
    "ptterm": "verde", 
    "dist": 6.938101110242019, 
    "enterm": "teal"
  }, 
  {
    "ptterm": "azul", 
    "dist": 4.446573983107494, 
    "enterm": "skyblue"
  }, 
  {
    "ptterm": "verde", 
    "dist": 11.097577401750103, 
    "enterm": "skyblue"
  }, 
  {
    "ptterm": "azul", 
    "dist": 8.491467651765763, 
    "enterm": "turquoise"
  }, 
  {
    "ptterm": "verde", 
    "dist": 7.1303877249512615, 
    "enterm": "turquoise"
  }, 
  {
    "ptterm": "azul", 
    "dist": 13.585585280261505, 
    "enterm": "lightgreen"
  }, 
  {
    "ptterm": "verde", 
    "dist": 1.873058963962518, 
    "enterm": "lightgreen"
  }, 
  {
    "ptterm": "azul", 
    "dist": 5.446018546905287, 
    "enterm": "violet"
  }, 
  {
    "ptterm": "verde", 
    "dist": 17.61427999914775, 
    "enterm": "violet"
  }, 
  {
    "ptterm": "azul", 
    "dist": 9.62252079285083, 
    "enterm": "hotpink"
  }, 
  {
    "ptterm": "verde", 
    "dist": 16.517573976773622, 
    "enterm": "hotpink"
  }, 
  {
    "ptterm": "azul", 
    "dist": 4.06792785517519, 
    "enterm": "darkblue"
  }, 
  {
    "ptterm": "verde", 
    "dist": 18.209828444860683, 
    "enterm": "darkblue"
  }, 
  {
    "ptterm": "azul", 
    "dist": 8.55767117648535, 
    "enterm": "fuchsia"
  }, 
  {
    "ptterm": "verde", 
    "dist": 17.268946178355232, 
    "enterm": "fuchsia"
  }, 
  {
    "ptterm": "azul", 
    "dist": 4.77432675384981, 
    "enterm": "royalblue"
  }, 
  {
    "ptterm": "verde", 
    "dist": 19.346590206380736, 
    "enterm": "royalblue"
  }, 
  {
    "ptterm": "azul", 
    "dist": 7.458701817202243, 
    "enterm": "gray"
  }, 
  {
    "ptterm": "verde", 
    "dist": 9.269817635216656, 
    "enterm": "gray"
  }, 
  {
    "ptterm": "azul", 
    "dist": 8.513149120289473, 
    "enterm": "aqua"
  }, 
  {
    "ptterm": "verde", 
    "dist": 7.237708254596933, 
    "enterm": "aqua"
  }, 
  {
    "ptterm": "azul", 
    "dist": 16.044439958013907, 
    "enterm": "neongreen"
  }, 
  {
    "ptterm": "verde", 
    "dist": 1.2093608165543834, 
    "enterm": "neongreen"
  }, 
  {
    "ptterm": "azul", 
    "dist": 7.654252323069832, 
    "enterm": "cyan"
  }, 
  {
    "ptterm": "verde", 
    "dist": 8.188563674382522, 
    "enterm": "cyan"
  }, 
  {
    "ptterm": "azul", 
    "dist": 10.404574811653864, 
    "enterm": "darkgreen"
  }, 
  {
    "ptterm": "verde", 
    "dist": 6.784621936595753, 
    "enterm": "darkgreen"
  }, 
  {
    "ptterm": "azul", 
    "dist": 15.402906064907652, 
    "enterm": "yellowgreen"
  }, 
  {
    "ptterm": "verde", 
    "dist": 3.077354762930336, 
    "enterm": "yellowgreen"
  }, 
  {
    "ptterm": "azul", 
    "dist": 15.484810251542607, 
    "enterm": "lime"
  }, 
  {
    "ptterm": "verde", 
    "dist": 1.8354038201078282, 
    "enterm": "lime"
  }, 
  {
    "ptterm": "azul", 
    "dist": 10.041654051182329, 
    "enterm": "maroon"
  }, 
  {
    "ptterm": "verde", 
    "dist": 12.985194030370224, 
    "enterm": "maroon"
  }, 
  {
    "ptterm": "azul", 
    "dist": 4.576043740221674, 
    "enterm": "lavender"
  }, 
  {
    "ptterm": "verde", 
    "dist": 13.930684264926029, 
    "enterm": "lavender"
  }, 
  {
    "ptterm": "azul", 
    "dist": 10.764782543250698, 
    "enterm": "forestgreen"
  }, 
  {
    "ptterm": "verde", 
    "dist": 6.218906433519004, 
    "enterm": "forestgreen"
  }, 
  {
    "ptterm": "azul", 
    "dist": 3.989303333798536, 
    "enterm": "navyblue"
  }, 
  {
    "ptterm": "verde", 
    "dist": 15.33861525372263, 
    "enterm": "navyblue"
  }, 
  {
    "ptterm": "azul", 
    "dist": 15.30012987865777, 
    "enterm": "brightgreen"
  }, 
  {
    "ptterm": "verde", 
    "dist": 1.0273760192409958, 
    "enterm": "brightgreen"
  }, 
  {
    "ptterm": "azul", 
    "dist": 4.420390976296387, 
    "enterm": "indigo"
  }, 
  {
    "ptterm": "verde", 
    "dist": 17.89794518055814, 
    "enterm": "indigo"
  }, 
  {
    "ptterm": "azul", 
    "dist": 14.501575123621263, 
    "enterm": "gold"
  }, 
  {
    "ptterm": "verde", 
    "dist": 7.263463852752911, 
    "enterm": "gold"
  }, 
  {
    "ptterm": "azul", 
    "dist": 5.766493433230688, 
    "enterm": "darkpurple"
  }, 
  {
    "ptterm": "verde", 
    "dist": 15.620761401590126, 
    "enterm": "darkpurple"
  }, 
  {
    "ptterm": "azul", 
    "dist": 11.896348011774247, 
    "enterm": "mintgreen"
  }, 
  {
    "ptterm": "verde", 
    "dist": 3.5736803478166244, 
    "enterm": "mintgreen"
  }, 
  {
    "ptterm": "azul", 
    "dist": 5.15368678631242, 
    "enterm": "lightpurple"
  }, 
  {
    "ptterm": "verde", 
    "dist": 15.955086391626391, 
    "enterm": "lightpurple"
  }, 
  {
    "ptterm": "azul", 
    "dist": 11.288517903411533, 
    "enterm": "mint"
  }, 
  {
    "ptterm": "verde", 
    "dist": 4.1008321023833485, 
    "enterm": "mint"
  }, 
  {
    "ptterm": "azul", 
    "dist": 10.779127431844342, 
    "enterm": "tan"
  }, 
  {
    "ptterm": "verde", 
    "dist": 7.810400420587842, 
    "enterm": "tan"
  }, 
  {
    "ptterm": "azul", 
    "dist": 4.6934122870502355, 
    "enterm": "lilac"
  }, 
  {
    "ptterm": "verde", 
    "dist": 13.892139905357975, 
    "enterm": "lilac"
  }, 
  {
    "ptterm": "azul", 
    "dist": 9.672415793684978, 
    "enterm": "darkpink"
  }, 
  {
    "ptterm": "verde", 
    "dist": 15.1337216684937, 
    "enterm": "darkpink"
  }, 
  {
    "ptterm": "azul", 
    "dist": 8.510513153441611, 
    "enterm": "black"
  }, 
  {
    "ptterm": "verde", 
    "dist": 11.70124725373444, 
    "enterm": "black"
  }, 
  {
    "ptterm": "azul", 
    "dist": 5.318890713078029, 
    "enterm": "babyblue"
  }, 
  {
    "ptterm": "verde", 
    "dist": 10.153359951234878, 
    "enterm": "babyblue"
  }, 
  {
    "ptterm": "azul", 
    "dist": 4.348033431766778, 
    "enterm": "navy"
  }, 
  {
    "ptterm": "verde", 
    "dist": 15.376671429435108, 
    "enterm": "navy"
  }, 
  {
    "ptterm": "azul", 
    "dist": 10.196773403073482, 
    "enterm": "beige"
  }, 
  {
    "ptterm": "verde", 
    "dist": 7.696419367146573, 
    "enterm": "beige"
  }, 
  {
    "ptterm": "azul", 
    "dist": 14.170029879290365, 
    "enterm": "mustard"
  }, 
  {
    "ptterm": "verde", 
    "dist": 6.906512221013534, 
    "enterm": "mustard"
  }, 
  {
    "ptterm": "azul", 
    "dist": 6.652601053717209, 
    "enterm": "mauve"
  }, 
  {
    "ptterm": "verde", 
    "dist": 12.989890057060132, 
    "enterm": "mauve"
  }, 
  {
    "ptterm": "azul", 
    "dist": 11.705669182409112, 
    "enterm": "olive"
  }, 
  {
    "ptterm": "verde", 
    "dist": 5.86797727346685, 
    "enterm": "olive"
  }, 
  {
    "ptterm": "azul", 
    "dist": 11.462206974123164, 
    "enterm": "seafoamgreen"
  }, 
  {
    "ptterm": "verde", 
    "dist": 4.009723905085854, 
    "enterm": "seafoamgreen"
  }, 
  {
    "ptterm": "azul", 
    "dist": 10.59059703515955, 
    "enterm": "peach"
  }, 
  {
    "ptterm": "verde", 
    "dist": 9.533809278225222, 
    "enterm": "peach"
  }, 
  {
    "ptterm": "azul", 
    "dist": 15.154096835632647, 
    "enterm": "redorange"
  }, 
  {
    "ptterm": "verde", 
    "dist": 13.234807434854224, 
    "enterm": "redorange"
  }, 
  {
    "ptterm": "azul", 
    "dist": 9.373401423015629, 
    "enterm": "bluegreen"
  }, 
  {
    "ptterm": "verde", 
    "dist": 6.001009178059295, 
    "enterm": "bluegreen"
  }, 
  {
    "ptterm": "azul", 
    "dist": 14.063994548456485, 
    "enterm": "burntorange"
  }, 
  {
    "ptterm": "verde", 
    "dist": 11.248462851319823, 
    "enterm": "burntorange"
  }, 
  {
    "ptterm": "azul", 
    "dist": 9.750626781340875, 
    "enterm": "rose"
  }, 
  {
    "ptterm": "verde", 
    "dist": 13.974251235122685, 
    "enterm": "rose"
  }, 
  {
    "ptterm": "azul", 
    "dist": 10.976670458465026, 
    "enterm": "seagreen"
  }, 
  {
    "ptterm": "verde", 
    "dist": 4.389021928773469, 
    "enterm": "seagreen"
  }, 
  {
    "ptterm": "azul", 
    "dist": 3.4379137332773637, 
    "enterm": "periwinkle"
  }, 
  {
    "ptterm": "verde", 
    "dist": 13.167481376709581, 
    "enterm": "periwinkle"
  }, 
  {
    "ptterm": "azul", 
    "dist": 10.994007915903117, 
    "enterm": "seafoam"
  }, 
  {
    "ptterm": "verde", 
    "dist": 4.425874106044547, 
    "enterm": "seafoam"
  }, 
  {
    "ptterm": "azul", 
    "dist": 10.471707328717322, 
    "enterm": "salmon"
  }, 
  {
    "ptterm": "verde", 
    "dist": 11.727448675834209, 
    "enterm": "salmon"
  }, 
  {
    "ptterm": "azul", 
    "dist": 15.141654062802466, 
    "enterm": "yelloworange"
  }, 
  {
    "ptterm": "verde", 
    "dist": 8.604611566405532, 
    "enterm": "yelloworange"
  }, 
  {
    "ptterm": "azul", 
    "dist": 1.773587449635398, 
    "enterm": "brightblue"
  }, 
  {
    "ptterm": "verde", 
    "dist": 13.76690764068847, 
    "enterm": "brightblue"
  }, 
  {
    "ptterm": "azul", 
    "dist": 11.526103590285214, 
    "enterm": "olivegreen"
  }, 
  {
    "ptterm": "verde", 
    "dist": 5.758255529207388, 
    "enterm": "olivegreen"
  }, 
  {
    "ptterm": "azul", 
    "dist": 9.820060696411375, 
    "enterm": "burgundy"
  }, 
  {
    "ptterm": "verde", 
    "dist": 13.012366900546775, 
    "enterm": "burgundy"
  }, 
  {
    "ptterm": "azul", 
    "dist": 13.619928997034158, 
    "enterm": "grassgreen"
  }, 
  {
    "ptterm": "verde", 
    "dist": 2.472486665229564, 
    "enterm": "grassgreen"
  }, 
  {
    "ptterm": "azul", 
    "dist": 15.361163185886097, 
    "enterm": "chartreuse"
  }, 
  {
    "ptterm": "verde", 
    "dist": 3.1466707906409, 
    "enterm": "chartreuse"
  }, 
  {
    "ptterm": "azul", 
    "dist": 8.619052153112353, 
    "enterm": "aquamarine"
  }, 
  {
    "ptterm": "verde", 
    "dist": 6.9387863498205595, 
    "enterm": "aquamarine"
  }, 
  {
    "ptterm": "azul", 
    "dist": 14.429127860522492, 
    "enterm": "darkorange"
  }, 
  {
    "ptterm": "verde", 
    "dist": 11.822216956172412, 
    "enterm": "darkorange"
  }, 
  {
    "ptterm": "azul", 
    "dist": 10.801561505197666, 
    "enterm": "lightbrown"
  }, 
  {
    "ptterm": "verde", 
    "dist": 8.900109051309837, 
    "enterm": "lightbrown"
  }, 
  {
    "ptterm": "azul", 
    "dist": 1.456109647818887, 
    "enterm": "cerulean"
  }, 
  {
    "ptterm": "verde", 
    "dist": 14.602511902728354, 
    "enterm": "cerulean"
  }, 
  {
    "ptterm": "azul", 
    "dist": 6.634311168466354, 
    "enterm": "brightpurple"
  }, 
  {
    "ptterm": "verde", 
    "dist": 18.933237557580203, 
    "enterm": "brightpurple"
  }, 
  {
    "ptterm": "azul", 
    "dist": 6.854345241621836, 
    "enterm": "lightpink"
  }, 
  {
    "ptterm": "verde", 
    "dist": 12.777030356724135, 
    "enterm": "lightpink"
  }, 
  {
    "ptterm": "azul", 
    "dist": 11.406059601875352, 
    "enterm": "palegreen"
  }, 
  {
    "ptterm": "verde", 
    "dist": 4.099754379799318, 
    "enterm": "palegreen"
  }, 
  {
    "ptterm": "azul", 
    "dist": 6.880478534004656, 
    "enterm": "plum"
  }, 
  {
    "ptterm": "verde", 
    "dist": 14.262923356575005, 
    "enterm": "plum"
  }, 
  {
    "ptterm": "azul", 
    "dist": 14.443384317966924, 
    "enterm": "lightorange"
  }, 
  {
    "ptterm": "verde", 
    "dist": 9.078422930390602, 
    "enterm": "lightorange"
  }, 
  {
    "ptterm": "azul", 
    "dist": 11.784868351691655, 
    "enterm": "darkred"
  }, 
  {
    "ptterm": "verde", 
    "dist": 13.069891919810143, 
    "enterm": "darkred"
  }, 
  {
    "ptterm": "azul", 
    "dist": 14.502061314938885, 
    "enterm": "darkyellow"
  }, 
  {
    "ptterm": "verde", 
    "dist": 6.671974465356701, 
    "enterm": "darkyellow"
  }, 
  {
    "ptterm": "azul", 
    "dist": 14.47921510732566, 
    "enterm": "mustardyellow"
  }, 
  {
    "ptterm": "verde", 
    "dist": 6.679333925361824, 
    "enterm": "mustardyellow"
  }, 
  {
    "ptterm": "azul", 
    "dist": 8.959513302401115, 
    "enterm": "brightpink"
  }, 
  {
    "ptterm": "verde", 
    "dist": 16.82613485350886, 
    "enterm": "brightpink"
  }, 
  {
    "ptterm": "azul", 
    "dist": 14.980702962340102, 
    "enterm": "goldenrod"
  }, 
  {
    "ptterm": "verde", 
    "dist": 7.748396460114158, 
    "enterm": "goldenrod"
  }, 
  {
    "ptterm": "azul", 
    "dist": 5.304351982773748, 
    "enterm": "royalpurple"
  }, 
  {
    "ptterm": "verde", 
    "dist": 17.539209502204542, 
    "enterm": "royalpurple"
  }, 
  {
    "ptterm": "azul", 
    "dist": 8.420079287642205, 
    "enterm": "fushia"
  }, 
  {
    "ptterm": "verde", 
    "dist": 17.40742795475446, 
    "enterm": "fushia"
  }, 
  {
    "ptterm": "azul", 
    "dist": 11.366794368936022, 
    "enterm": "pastelgreen"
  }, 
  {
    "ptterm": "verde", 
    "dist": 4.06113360195763, 
    "enterm": "pastelgreen"
  }, 
  {
    "ptterm": "azul", 
    "dist": 15.27360862636685, 
    "enterm": "greenyellow"
  }, 
  {
    "ptterm": "verde", 
    "dist": 2.861529931177083, 
    "enterm": "greenyellow"
  }, 
  {
    "ptterm": "azul", 
    "dist": 12.20962184272521, 
    "enterm": "crimson"
  }, 
  {
    "ptterm": "verde", 
    "dist": 13.867286306018862, 
    "enterm": "crimson"
  }, 
  {
    "ptterm": "azul", 
    "dist": 2.054727157744662, 
    "enterm": "oceanblue"
  }, 
  {
    "ptterm": "verde", 
    "dist": 13.670043047738734, 
    "enterm": "oceanblue"
  }, 
  {
    "ptterm": "azul", 
    "dist": 12.203131172658505, 
    "enterm": "brickred"
  }, 
  {
    "ptterm": "verde", 
    "dist": 12.757115295832756, 
    "enterm": "brickred"
  }, 
  {
    "ptterm": "azul", 
    "dist": 1.702434876739692, 
    "enterm": "mediumblue"
  }, 
  {
    "ptterm": "verde", 
    "dist": 15.394280065772232, 
    "enterm": "mediumblue"
  }, 
  {
    "ptterm": "azul", 
    "dist": 3.4777922311329363, 
    "enterm": "cobalt"
  }, 
  {
    "ptterm": "verde", 
    "dist": 17.927913156659393, 
    "enterm": "cobalt"
  }, 
  {
    "ptterm": "azul", 
    "dist": 7.101528063583139, 
    "enterm": "neonblue"
  }, 
  {
    "ptterm": "verde", 
    "dist": 8.889951082202858, 
    "enterm": "neonblue"
  }, 
  {
    "ptterm": "azul", 
    "dist": 11.071974102119798, 
    "enterm": "coral"
  }, 
  {
    "ptterm": "verde", 
    "dist": 12.45969750427526, 
    "enterm": "coral"
  }, 
  {
    "ptterm": "azul", 
    "dist": 9.604916256972372, 
    "enterm": "darkbrown"
  }, 
  {
    "ptterm": "verde", 
    "dist": 11.07924644481418, 
    "enterm": "darkbrown"
  }, 
  {
    "ptterm": "azul", 
    "dist": 8.643660904484555, 
    "enterm": "neonpink"
  }, 
  {
    "ptterm": "verde", 
    "dist": 17.8595530964391, 
    "enterm": "neonpink"
  }, 
  {
    "ptterm": "azul", 
    "dist": 10.933663648457143, 
    "enterm": "khaki"
  }, 
  {
    "ptterm": "verde", 
    "dist": 6.660630076577861, 
    "enterm": "khaki"
  }, 
  {
    "ptterm": "azul", 
    "dist": 1.2309666461074014, 
    "enterm": "electricblue"
  }, 
  {
    "ptterm": "verde", 
    "dist": 15.532818701813877, 
    "enterm": "electricblue"
  }, 
  {
    "ptterm": "azul", 
    "dist": 6.356517248648787, 
    "enterm": "bluegray"
  }, 
  {
    "ptterm": "verde", 
    "dist": 9.805495612789707, 
    "enterm": "bluegray"
  }, 
  {
    "ptterm": "azul", 
    "dist": 3.654493122237392, 
    "enterm": "seablue"
  }, 
  {
    "ptterm": "verde", 
    "dist": 11.675802364698464, 
    "enterm": "seablue"
  }, 
  {
    "ptterm": "azul", 
    "dist": 10.921178769932267, 
    "enterm": "armygreen"
  }, 
  {
    "ptterm": "verde", 
    "dist": 6.67158052930422, 
    "enterm": "armygreen"
  }, 
  {
    "ptterm": "azul", 
    "dist": 14.314202053976357, 
    "enterm": "springgreen"
  }, 
  {
    "ptterm": "verde", 
    "dist": 1.3129017568659496, 
    "enterm": "springgreen"
  }, 
  {
    "ptterm": "azul", 
    "dist": 7.411046107848756, 
    "enterm": "neonpurple"
  }, 
  {
    "ptterm": "verde", 
    "dist": 19.51426111508005, 
    "enterm": "neonpurple"
  }, 
  {
    "ptterm": "azul", 
    "dist": 14.623948590988041, 
    "enterm": "orangered"
  }, 
  {
    "ptterm": "verde", 
    "dist": 13.251198543071318, 
    "enterm": "orangered"
  }, 
  {
    "ptterm": "azul", 
    "dist": 5.644559964626226, 
    "enterm": "grayblue"
  }, 
  {
    "ptterm": "verde", 
    "dist": 10.509126894766547, 
    "enterm": "grayblue"
  }, 
  {
    "ptterm": "azul", 
    "dist": 12.992557434483711, 
    "enterm": "kellygreen"
  }, 
  {
    "ptterm": "verde", 
    "dist": 2.8996098828030075, 
    "enterm": "kellygreen"
  }, 
  {
    "ptterm": "azul", 
    "dist": 16.544698874933662, 
    "enterm": "neonyellow"
  }, 
  {
    "ptterm": "verde", 
    "dist": 4.724006473168332, 
    "enterm": "neonyellow"
  }, 
  {
    "ptterm": "azul", 
    "dist": 9.94184102760863, 
    "enterm": "greenblue"
  }, 
  {
    "ptterm": "verde", 
    "dist": 5.5143637315720735, 
    "enterm": "greenblue"
  }, 
  {
    "ptterm": "azul", 
    "dist": 4.7531909433642, 
    "enterm": "bluepurple"
  }, 
  {
    "ptterm": "verde", 
    "dist": 18.498839787088254, 
    "enterm": "bluepurple"
  }, 
  {
    "ptterm": "azul", 
    "dist": 3.6928422487869903, 
    "enterm": "cobaltblue"
  }, 
  {
    "ptterm": "verde", 
    "dist": 18.332062507636273, 
    "enterm": "cobaltblue"
  }, 
  {
    "ptterm": "azul", 
    "dist": 13.643383567387986, 
    "enterm": "scarlet"
  }, 
  {
    "ptterm": "verde", 
    "dist": 14.253270698183849, 
    "enterm": "scarlet"
  }, 
  {
    "ptterm": "azul", 
    "dist": 7.634436611232225, 
    "enterm": "pinkpurple"
  }, 
  {
    "ptterm": "verde", 
    "dist": 17.622577795036527, 
    "enterm": "pinkpurple"
  }, 
  {
    "ptterm": "azul", 
    "dist": 12.363463255133885, 
    "enterm": "redpink"
  }, 
  {
    "ptterm": "verde", 
    "dist": 15.180263287024285, 
    "enterm": "redpink"
  }, 
  {
    "ptterm": "azul", 
    "dist": 12.457595028918796, 
    "enterm": "rust"
  }, 
  {
    "ptterm": "verde", 
    "dist": 11.411121220116518, 
    "enterm": "rust"
  }, 
  {
    "ptterm": "azul", 
    "dist": 7.439226963943674, 
    "enterm": "purplepink"
  }, 
  {
    "ptterm": "verde", 
    "dist": 17.393985115423533, 
    "enterm": "purplepink"
  }, 
  {
    "ptterm": "azul", 
    "dist": 9.91298825297377, 
    "enterm": "huntergreen"
  }, 
  {
    "ptterm": "verde", 
    "dist": 7.308338058259009, 
    "enterm": "huntergreen"
  }, 
  {
    "ptterm": "azul", 
    "dist": 10.684399092121515, 
    "enterm": "cream"
  }, 
  {
    "ptterm": "verde", 
    "dist": 7.134687571541866, 
    "enterm": "cream"
  }, 
  {
    "ptterm": "azul", 
    "dist": 5.222475685993843, 
    "enterm": "paleblue"
  }, 
  {
    "ptterm": "verde", 
    "dist": 10.262502329305331, 
    "enterm": "paleblue"
  }, 
  {
    "ptterm": "azul", 
    "dist": 8.919523763614059, 
    "enterm": "taupe"
  }, 
  {
    "ptterm": "verde", 
    "dist": 8.719524372392431, 
    "enterm": "taupe"
  }, 
  {
    "ptterm": "azul", 
    "dist": 14.424811793022043, 
    "enterm": "tangerine"
  }, 
  {
    "ptterm": "verde", 
    "dist": 10.091002923861392, 
    "enterm": "tangerine"
  }, 
  {
    "ptterm": "azul", 
    "dist": 2.2255003135489564, 
    "enterm": "cornflowerblue"
  }, 
  {
    "ptterm": "verde", 
    "dist": 14.578457819605518, 
    "enterm": "cornflowerblue"
  }, 
  {
    "ptterm": "azul", 
    "dist": 9.8851255117392, 
    "enterm": "sage"
  }, 
  {
    "ptterm": "verde", 
    "dist": 6.172208136578524, 
    "enterm": "sage"
  }, 
  {
    "ptterm": "azul", 
    "dist": 4.6167546900269905, 
    "enterm": "midnightblue"
  }, 
  {
    "ptterm": "verde", 
    "dist": 15.646201520802286, 
    "enterm": "midnightblue"
  }, 
  {
    "ptterm": "azul", 
    "dist": 13.134004867213331, 
    "enterm": "ochre"
  }, 
  {
    "ptterm": "verde", 
    "dist": 7.91206594540874, 
    "enterm": "ochre"
  }, 
  {
    "ptterm": "azul", 
    "dist": 11.260691722230948, 
    "enterm": "mossgreen"
  }, 
  {
    "ptterm": "verde", 
    "dist": 5.3775960242145615, 
    "enterm": "mossgreen"
  }, 
  {
    "ptterm": "azul", 
    "dist": 13.22248652809283, 
    "enterm": "leafgreen"
  }, 
  {
    "ptterm": "verde", 
    "dist": 2.6852252708482083, 
    "enterm": "leafgreen"
  }, 
  {
    "ptterm": "azul", 
    "dist": 4.578335523963965, 
    "enterm": "lavendar"
  }, 
  {
    "ptterm": "verde", 
    "dist": 13.94076766617893, 
    "enterm": "lavendar"
  }, 
  {
    "ptterm": "azul", 
    "dist": 6.448457302312673, 
    "enterm": "eggplant"
  }, 
  {
    "ptterm": "verde", 
    "dist": 14.718181943151743, 
    "enterm": "eggplant"
  }, 
  {
    "ptterm": "azul", 
    "dist": 7.579078035737447, 
    "enterm": "babypink"
  }, 
  {
    "ptterm": "verde", 
    "dist": 11.675108833336582, 
    "enterm": "babypink"
  }, 
  {
    "ptterm": "azul", 
    "dist": 6.9143462670894, 
    "enterm": "darkteal"
  }, 
  {
    "ptterm": "verde", 
    "dist": 9.290577079718814, 
    "enterm": "darkteal"
  }, 
  {
    "ptterm": "azul", 
    "dist": 11.411161042756145, 
    "enterm": "emerald"
  }, 
  {
    "ptterm": "verde", 
    "dist": 4.089876328991359, 
    "enterm": "emerald"
  }, 
  {
    "ptterm": "azul", 
    "dist": 8.76160365229377, 
    "enterm": "graygreen"
  }, 
  {
    "ptterm": "verde", 
    "dist": 7.361829606213295, 
    "enterm": "graygreen"
  }, 
  {
    "ptterm": "azul", 
    "dist": 2.197728507230031, 
    "enterm": "azure"
  }, 
  {
    "ptterm": "verde", 
    "dist": 13.158324241018127, 
    "enterm": "azure"
  }, 
  {
    "ptterm": "azul", 
    "dist": 13.692340453193834, 
    "enterm": "peagreen"
  }, 
  {
    "ptterm": "verde", 
    "dist": 3.6025369298577434, 
    "enterm": "peagreen"
  }, 
  {
    "ptterm": "azul", 
    "dist": 12.420444808058713, 
    "enterm": "pinkred"
  }, 
  {
    "ptterm": "verde", 
    "dist": 15.020809937701422, 
    "enterm": "pinkred"
  }, 
  {
    "ptterm": "azul", 
    "dist": 10.62049930423969, 
    "enterm": "raspberry"
  }, 
  {
    "ptterm": "verde", 
    "dist": 15.152226900240617, 
    "enterm": "raspberry"
  }, 
  {
    "ptterm": "azul", 
    "dist": 7.050536004722655, 
    "enterm": "aquablue"
  }, 
  {
    "ptterm": "verde", 
    "dist": 8.753982743037225, 
    "enterm": "aquablue"
  }, 
  {
    "ptterm": "azul", 
    "dist": 6.742583368401989, 
    "enterm": "robinseggblue"
  }, 
  {
    "ptterm": "verde", 
    "dist": 8.86931805337174, 
    "enterm": "robinseggblue"
  }, 
  {
    "ptterm": "azul", 
    "dist": 13.660860332645422, 
    "enterm": "lightyellow"
  }, 
  {
    "ptterm": "verde", 
    "dist": 5.345564632255698, 
    "enterm": "lightyellow"
  }, 
  {
    "ptterm": "azul", 
    "dist": 15.297308815693288, 
    "enterm": "goldenyellow"
  }, 
  {
    "ptterm": "verde", 
    "dist": 7.436532688238028, 
    "enterm": "goldenyellow"
  }, 
  {
    "ptterm": "azul", 
    "dist": 4.379669999267744, 
    "enterm": "deepblue"
  }, 
  {
    "ptterm": "verde", 
    "dist": 18.64396183079402, 
    "enterm": "deepblue"
  }, 
  {
    "ptterm": "azul", 
    "dist": 14.417536315138628, 
    "enterm": "brightred"
  }, 
  {
    "ptterm": "verde", 
    "dist": 14.457956343377168, 
    "enterm": "brightred"
  }, 
  {
    "ptterm": "azul", 
    "dist": 6.528488594307539, 
    "enterm": "orchid"
  }, 
  {
    "ptterm": "verde", 
    "dist": 16.459968340219834, 
    "enterm": "orchid"
  }, 
  {
    "ptterm": "azul", 
    "dist": 12.742940739036502, 
    "enterm": "paleyellow"
  }, 
  {
    "ptterm": "verde", 
    "dist": 5.669472603293541, 
    "enterm": "paleyellow"
  }, 
  {
    "ptterm": "azul", 
    "dist": 9.208320150639164, 
    "enterm": "wine"
  }, 
  {
    "ptterm": "verde", 
    "dist": 13.449975915313637, 
    "enterm": "wine"
  }, 
  {
    "ptterm": "azul", 
    "dist": 11.966628181762117, 
    "enterm": "sienna"
  }, 
  {
    "ptterm": "verde", 
    "dist": 10.173874542181135, 
    "enterm": "sienna"
  }, 
  {
    "ptterm": "azul", 
    "dist": 9.874943797833375, 
    "enterm": "burgandy"
  }, 
  {
    "ptterm": "verde", 
    "dist": 13.299414153815873, 
    "enterm": "burgandy"
  }, 
  {
    "ptterm": "azul", 
    "dist": 11.755762819726856, 
    "enterm": "lightred"
  }, 
  {
    "ptterm": "verde", 
    "dist": 13.577901356972395, 
    "enterm": "lightred"
  }, 
  {
    "ptterm": "azul", 
    "dist": 13.96836361761771, 
    "enterm": "applegreen"
  }, 
  {
    "ptterm": "verde", 
    "dist": 1.8749182528951376, 
    "enterm": "applegreen"
  }, 
  {
    "ptterm": "azul", 
    "dist": 4.332519306828559, 
    "enterm": "purpleblue"
  }, 
  {
    "ptterm": "verde", 
    "dist": 18.312077986883086, 
    "enterm": "purpleblue"
  }, 
  {
    "ptterm": "azul", 
    "dist": 4.265063536287738, 
    "enterm": "powderblue"
  }, 
  {
    "ptterm": "verde", 
    "dist": 11.612105615857685, 
    "enterm": "powderblue"
  }, 
  {
    "ptterm": "azul", 
    "dist": 7.65470241629731, 
    "enterm": "darkgray"
  }, 
  {
    "ptterm": "verde", 
    "dist": 10.332272815751537, 
    "enterm": "darkgray"
  }, 
  {
    "ptterm": "azul", 
    "dist": 11.378659277399121, 
    "enterm": "sand"
  }, 
  {
    "ptterm": "verde", 
    "dist": 7.269538064825648, 
    "enterm": "sand"
  }, 
  {
    "ptterm": "azul", 
    "dist": 5.55677964931314, 
    "enterm": "deeppurple"
  }, 
  {
    "ptterm": "verde", 
    "dist": 16.072977332528403, 
    "enterm": "deeppurple"
  }, 
  {
    "ptterm": "azul", 
    "dist": 9.0307962123742, 
    "enterm": "rosepink"
  }, 
  {
    "ptterm": "verde", 
    "dist": 13.812167315560004, 
    "enterm": "rosepink"
  }, 
  {
    "ptterm": "azul", 
    "dist": 2.3702059390470094, 
    "enterm": "cornflower"
  }, 
  {
    "ptterm": "verde", 
    "dist": 14.10285426732159, 
    "enterm": "cornflower"
  }, 
  {
    "ptterm": "azul", 
    "dist": 9.281570050248549, 
    "enterm": "lightteal"
  }, 
  {
    "ptterm": "verde", 
    "dist": 6.185788984727293, 
    "enterm": "lightteal"
  }, 
  {
    "ptterm": "azul", 
    "dist": 13.813074433720173, 
    "enterm": "pukegreen"
  }, 
  {
    "ptterm": "verde", 
    "dist": 3.9297901764318857, 
    "enterm": "pukegreen"
  }, 
  {
    "ptterm": "azul", 
    "dist": 11.773272234320387, 
    "enterm": "emeraldgreen"
  }, 
  {
    "ptterm": "verde", 
    "dist": 3.8843538901657904, 
    "enterm": "emeraldgreen"
  }, 
  {
    "ptterm": "azul", 
    "dist": 7.667940686099595, 
    "enterm": "pinkishpurple"
  }, 
  {
    "ptterm": "verde", 
    "dist": 17.9171787338245, 
    "enterm": "pinkishpurple"
  }, 
  {
    "ptterm": "azul", 
    "dist": 8.353511487889119, 
    "enterm": "fusia"
  }, 
  {
    "ptterm": "verde", 
    "dist": 17.921802828951403, 
    "enterm": "fusia"
  }, 
  {
    "ptterm": "azul", 
    "dist": 8.138156557112227, 
    "enterm": "darkmagenta"
  }, 
  {
    "ptterm": "verde", 
    "dist": 15.126726775940762, 
    "enterm": "darkmagenta"
  }, 
  {
    "ptterm": "azul", 
    "dist": 16.59783861272579, 
    "enterm": "brightyellow"
  }, 
  {
    "ptterm": "verde", 
    "dist": 5.712988170264804, 
    "enterm": "brightyellow"
  }, 
  {
    "ptterm": "azul", 
    "dist": 12.2803478150784, 
    "enterm": "pinkishred"
  }, 
  {
    "ptterm": "verde", 
    "dist": 14.956971479030864, 
    "enterm": "pinkishred"
  }, 
  {
    "ptterm": "azul", 
    "dist": 16.25417864142385, 
    "enterm": "lemonyellow"
  }, 
  {
    "ptterm": "verde", 
    "dist": 5.4381787158375365, 
    "enterm": "lemonyellow"
  }, 
  {
    "ptterm": "azul", 
    "dist": 15.015642693575002, 
    "enterm": "marigold"
  }, 
  {
    "ptterm": "verde", 
    "dist": 7.984053613402027, 
    "enterm": "marigold"
  }, 
  {
    "ptterm": "azul", 
    "dist": 9.676687555897344, 
    "enterm": "puce"
  }, 
  {
    "ptterm": "verde", 
    "dist": 8.618045416786746, 
    "enterm": "puce"
  }, 
  {
    "ptterm": "azul", 
    "dist": 11.157664896107987, 
    "enterm": "redbrown"
  }, 
  {
    "ptterm": "verde", 
    "dist": 11.691529597300526, 
    "enterm": "redbrown"
  }, 
  {
    "ptterm": "azul", 
    "dist": 10.139774907526494, 
    "enterm": "jade"
  }, 
  {
    "ptterm": "verde", 
    "dist": 5.321760519727312, 
    "enterm": "jade"
  }, 
  {
    "ptterm": "azul", 
    "dist": 14.349625713266025, 
    "enterm": "pumpkin"
  }, 
  {
    "ptterm": "verde", 
    "dist": 10.33953840867409, 
    "enterm": "pumpkin"
  }, 
  {
    "ptterm": "azul", 
    "dist": 5.106217894629186, 
    "enterm": "grape"
  }, 
  {
    "ptterm": "verde", 
    "dist": 16.57375098633003, 
    "enterm": "grape"
  }, 
  {
    "ptterm": "azul", 
    "dist": 8.807720196966555, 
    "enterm": "white"
  }, 
  {
    "ptterm": "verde", 
    "dist": 8.269912498828328, 
    "enterm": "white"
  }, 
  {
    "ptterm": "azul", 
    "dist": 11.25989182615858, 
    "enterm": "moss"
  }, 
  {
    "ptterm": "verde", 
    "dist": 5.493424692803275, 
    "enterm": "moss"
  }, 
  {
    "ptterm": "azul", 
    "dist": 8.345273525382124, 
    "enterm": "dustyrose"
  }, 
  {
    "ptterm": "verde", 
    "dist": 11.698049009644231, 
    "enterm": "dustyrose"
  }, 
  {
    "ptterm": "azul", 
    "dist": 3.4661597564416433, 
    "enterm": "ultramarine"
  }, 
  {
    "ptterm": "verde", 
    "dist": 17.975952302650814, 
    "enterm": "ultramarine"
  }, 
  {
    "ptterm": "azul", 
    "dist": 11.667522974331822, 
    "enterm": "brick"
  }, 
  {
    "ptterm": "verde", 
    "dist": 12.031096942870263, 
    "enterm": "brick"
  }, 
  {
    "ptterm": "azul", 
    "dist": 5.15581376747647, 
    "enterm": "blueviolet"
  }, 
  {
    "ptterm": "verde", 
    "dist": 18.76082095014173, 
    "enterm": "blueviolet"
  }, 
  {
    "ptterm": "azul", 
    "dist": 15.734715957319686, 
    "enterm": "yello"
  }, 
  {
    "ptterm": "verde", 
    "dist": 5.8125351182069, 
    "enterm": "yello"
  }, 
  {
    "ptterm": "azul", 
    "dist": 8.166820414568466, 
    "enterm": "lightgray"
  }, 
  {
    "ptterm": "verde", 
    "dist": 8.746757820192196, 
    "enterm": "lightgray"
  }, 
  {
    "ptterm": "azul", 
    "dist": 10.01728922324421, 
    "enterm": "pinegreen"
  }, 
  {
    "ptterm": "verde", 
    "dist": 6.75843619922809, 
    "enterm": "pinegreen"
  }, 
  {
    "ptterm": "azul", 
    "dist": 10.448390230571453, 
    "enterm": "deeppink"
  }, 
  {
    "ptterm": "verde", 
    "dist": 15.927798095621256, 
    "enterm": "deeppink"
  }, 
  {
    "ptterm": "azul", 
    "dist": 4.892614483744556, 
    "enterm": "pastelblue"
  }, 
  {
    "ptterm": "verde", 
    "dist": 10.665972333155802, 
    "enterm": "pastelblue"
  }, 
  {
    "ptterm": "azul", 
    "dist": 7.607921518834093, 
    "enterm": "palepink"
  }, 
  {
    "ptterm": "verde", 
    "dist": 11.018347812168308, 
    "enterm": "palepink"
  }, 
  {
    "ptterm": "azul", 
    "dist": 12.072158160566994, 
    "enterm": "burntsienna"
  }, 
  {
    "ptterm": "verde", 
    "dist": 10.657365723855436, 
    "enterm": "burntsienna"
  }, 
  {
    "ptterm": "azul", 
    "dist": 15.916776834363672, 
    "enterm": "greenishyellow"
  }, 
  {
    "ptterm": "verde", 
    "dist": 4.195984894999235, 
    "enterm": "greenishyellow"
  }, 
  {
    "ptterm": "azul", 
    "dist": 4.773602268315836, 
    "enterm": "slateblue"
  }, 
  {
    "ptterm": "verde", 
    "dist": 11.825886575374732, 
    "enterm": "slateblue"
  }, 
  {
    "ptterm": "azul", 
    "dist": 8.581239457913247, 
    "enterm": "redviolet"
  }, 
  {
    "ptterm": "verde", 
    "dist": 15.757711701038527, 
    "enterm": "redviolet"
  }, 
  {
    "ptterm": "azul", 
    "dist": 8.606144583783294, 
    "enterm": "lightturquoise"
  }, 
  {
    "ptterm": "verde", 
    "dist": 7.251168793755895, 
    "enterm": "lightturquoise"
  }, 
  {
    "ptterm": "azul", 
    "dist": 13.822309328115113, 
    "enterm": "grass"
  }, 
  {
    "ptterm": "verde", 
    "dist": 2.5045270321077995, 
    "enterm": "grass"
  }, 
  {
    "ptterm": "azul", 
    "dist": 12.559208346607873, 
    "enterm": "bloodred"
  }, 
  {
    "ptterm": "verde", 
    "dist": 13.54710354052252, 
    "enterm": "bloodred"
  }, 
  {
    "ptterm": "azul", 
    "dist": 10.270979270403608, 
    "enterm": "forrestgreen"
  }, 
  {
    "ptterm": "verde", 
    "dist": 6.909396964379381, 
    "enterm": "forrestgreen"
  }, 
  {
    "ptterm": "azul", 
    "dist": 9.843182638086173, 
    "enterm": "cerise"
  }, 
  {
    "ptterm": "verde", 
    "dist": 15.457962975834912, 
    "enterm": "cerise"
  }, 
  {
    "ptterm": "azul", 
    "dist": 11.935887477644656, 
    "enterm": "yellowbrown"
  }, 
  {
    "ptterm": "verde", 
    "dist": 7.962721459600135, 
    "enterm": "yellowbrown"
  }, 
  {
    "ptterm": "azul", 
    "dist": 6.649434517346219, 
    "enterm": "slate"
  }, 
  {
    "ptterm": "verde", 
    "dist": 9.901523316689396, 
    "enterm": "slate"
  }, 
  {
    "ptterm": "azul", 
    "dist": 10.17381586585535, 
    "enterm": "evergreen"
  }, 
  {
    "ptterm": "verde", 
    "dist": 6.60384047674241, 
    "enterm": "evergreen"
  }, 
  {
    "ptterm": "azul", 
    "dist": 15.518133054438058, 
    "enterm": "electricgreen"
  }, 
  {
    "ptterm": "verde", 
    "dist": 0.7605456121146963, 
    "enterm": "electricgreen"
  }, 
  {
    "ptterm": "azul", 
    "dist": 10.578864697506692, 
    "enterm": "sagegreen"
  }, 
  {
    "ptterm": "verde", 
    "dist": 5.335087659335635, 
    "enterm": "sagegreen"
  }, 
  {
    "ptterm": "azul", 
    "dist": 8.493252631613254, 
    "enterm": "blush"
  }, 
  {
    "ptterm": "verde", 
    "dist": 11.160463341165825, 
    "enterm": "blush"
  }, 
  {
    "ptterm": "azul", 
    "dist": 15.32972869227171, 
    "enterm": "dandelion"
  }, 
  {
    "ptterm": "verde", 
    "dist": 6.589611987717093, 
    "enterm": "dandelion"
  }, 
  {
    "ptterm": "azul", 
    "dist": 5.303608963629604, 
    "enterm": "steelblue"
  }, 
  {
    "ptterm": "verde", 
    "dist": 10.912488392710447, 
    "enterm": "steelblue"
  }, 
  {
    "ptterm": "azul", 
    "dist": 8.884424172943953, 
    "enterm": "turquiose"
  }, 
  {
    "ptterm": "verde", 
    "dist": 6.813649074977247, 
    "enterm": "turquiose"
  }, 
  {
    "ptterm": "azul", 
    "dist": 11.38868682202004, 
    "enterm": "reddishpink"
  }, 
  {
    "ptterm": "verde", 
    "dist": 14.91989972657292, 
    "enterm": "reddishpink"
  }, 
  {
    "ptterm": "azul", 
    "dist": 1.8844770444630188, 
    "enterm": "ceruleanblue"
  }, 
  {
    "ptterm": "verde", 
    "dist": 14.798694458976929, 
    "enterm": "ceruleanblue"
  }, 
  {
    "ptterm": "azul", 
    "dist": 5.5680803405738075, 
    "enterm": "pastelpurple"
  }, 
  {
    "ptterm": "verde", 
    "dist": 12.851301688209508, 
    "enterm": "pastelpurple"
  }, 
  {
    "ptterm": "azul", 
    "dist": 15.512674667659063, 
    "enterm": "lemon"
  }, 
  {
    "ptterm": "verde", 
    "dist": 4.997110970693968, 
    "enterm": "lemon"
  }, 
  {
    "ptterm": "azul", 
    "dist": 9.286629312661265, 
    "enterm": "turqouise"
  }, 
  {
    "ptterm": "verde", 
    "dist": 6.523123993857416, 
    "enterm": "turqouise"
  }, 
  {
    "ptterm": "azul", 
    "dist": 6.531186857105638, 
    "enterm": "graypurple"
  }, 
  {
    "ptterm": "verde", 
    "dist": 11.406684710669388, 
    "enterm": "graypurple"
  }, 
  {
    "ptterm": "azul", 
    "dist": 6.810833336337248, 
    "enterm": "tealblue"
  }, 
  {
    "ptterm": "verde", 
    "dist": 8.726666482041344, 
    "enterm": "tealblue"
  }, 
  {
    "ptterm": "azul", 
    "dist": 14.338038898495906, 
    "enterm": "dirtyyellow"
  }, 
  {
    "ptterm": "verde", 
    "dist": 5.623936645275951, 
    "enterm": "dirtyyellow"
  }, 
  {
    "ptterm": "azul", 
    "dist": 11.162374818532776, 
    "enterm": "reddishbrown"
  }, 
  {
    "ptterm": "verde", 
    "dist": 11.636297016566742, 
    "enterm": "reddishbrown"
  }, 
  {
    "ptterm": "azul", 
    "dist": 15.81448968306606, 
    "enterm": "fluorescentgreen"
  }, 
  {
    "ptterm": "verde", 
    "dist": 1.3078344605457282, 
    "enterm": "fluorescentgreen"
  }, 
  {
    "ptterm": "azul", 
    "dist": 2.9126314693958077, 
    "enterm": "denim"
  }, 
  {
    "ptterm": "verde", 
    "dist": 14.055152842703485, 
    "enterm": "denim"
  }, 
  {
    "ptterm": "azul", 
    "dist": 11.649134618493177, 
    "enterm": "terracotta"
  }, 
  {
    "ptterm": "verde", 
    "dist": 10.926652037796195, 
    "enterm": "terracotta"
  }, 
  {
    "ptterm": "azul", 
    "dist": 7.515013774889418, 
    "enterm": "pastelpink"
  }, 
  {
    "ptterm": "verde", 
    "dist": 11.746293723248273, 
    "enterm": "pastelpink"
  }, 
  {
    "ptterm": "azul", 
    "dist": 4.70082615769863, 
    "enterm": "lightviolet"
  }, 
  {
    "ptterm": "verde", 
    "dist": 15.067436338370849, 
    "enterm": "lightviolet"
  }, 
  {
    "ptterm": "azul", 
    "dist": 11.173489150456998, 
    "enterm": "aquagreen"
  }, 
  {
    "ptterm": "verde", 
    "dist": 4.459762926173793, 
    "enterm": "aquagreen"
  }, 
  {
    "ptterm": "azul", 
    "dist": 5.054943899089475, 
    "enterm": "palepurple"
  }, 
  {
    "ptterm": "verde", 
    "dist": 13.368963014687406, 
    "enterm": "palepurple"
  }, 
  {
    "ptterm": "azul", 
    "dist": 10.172366266994732, 
    "enterm": "mahogany"
  }, 
  {
    "ptterm": "verde", 
    "dist": 11.819071375531236, 
    "enterm": "mahogany"
  }, 
  {
    "ptterm": "azul", 
    "dist": 14.87387046236033, 
    "enterm": "yellowishgreen"
  }, 
  {
    "ptterm": "verde", 
    "dist": 3.2488644898887986, 
    "enterm": "yellowishgreen"
  }, 
  {
    "ptterm": "azul", 
    "dist": 13.013924010715952, 
    "enterm": "vermillion"
  }, 
  {
    "ptterm": "verde", 
    "dist": 13.841374019830555, 
    "enterm": "vermillion"
  }, 
  {
    "ptterm": "azul", 
    "dist": 13.476617901739393, 
    "enterm": "cherryred"
  }, 
  {
    "ptterm": "verde", 
    "dist": 14.62557253895994, 
    "enterm": "cherryred"
  }, 
  {
    "ptterm": "azul", 
    "dist": 4.909935961006854, 
    "enterm": "lavander"
  }, 
  {
    "ptterm": "verde", 
    "dist": 13.107030612662191, 
    "enterm": "lavander"
  }, 
  {
    "ptterm": "azul", 
    "dist": 8.097402769557178, 
    "enterm": "dustypink"
  }, 
  {
    "ptterm": "verde", 
    "dist": 11.423730813818707, 
    "enterm": "dustypink"
  }, 
  {
    "ptterm": "azul", 
    "dist": 12.382337170550606, 
    "enterm": "bronze"
  }, 
  {
    "ptterm": "verde", 
    "dist": 8.485341346676522, 
    "enterm": "bronze"
  }, 
  {
    "ptterm": "azul", 
    "dist": 11.319196132900805, 
    "enterm": "dullgreen"
  }, 
  {
    "ptterm": "verde", 
    "dist": 4.902459947704713, 
    "enterm": "dullgreen"
  }, 
  {
    "ptterm": "azul", 
    "dist": 11.462546428804496, 
    "enterm": "browngreen"
  }, 
  {
    "ptterm": "verde", 
    "dist": 6.838645325964685, 
    "enterm": "browngreen"
  }, 
  {
    "ptterm": "azul", 
    "dist": 7.659585389523333, 
    "enterm": "silver"
  }, 
  {
    "ptterm": "verde", 
    "dist": 9.086958408462047, 
    "enterm": "silver"
  }, 
  {
    "ptterm": "azul", 
    "dist": 10.152659523027584, 
    "enterm": "tealgreen"
  }, 
  {
    "ptterm": "verde", 
    "dist": 5.261452147695094, 
    "enterm": "tealgreen"
  }, 
  {
    "ptterm": "azul", 
    "dist": 7.261317324596749, 
    "enterm": "y"
  }, 
  {
    "ptterm": "verde", 
    "dist": 9.661945716429157, 
    "enterm": "y"
  }, 
  {
    "ptterm": "azul", 
    "dist": 10.376053205592532, 
    "enterm": "forest"
  }, 
  {
    "ptterm": "verde", 
    "dist": 6.427049450653044, 
    "enterm": "forest"
  }, 
  {
    "ptterm": "azul", 
    "dist": 8.85304890064882, 
    "enterm": "berry"
  }, 
  {
    "ptterm": "verde", 
    "dist": 14.929809625259367, 
    "enterm": "berry"
  }, 
  {
    "ptterm": "azul", 
    "dist": 11.93859026935967, 
    "enterm": "pistachio"
  }, 
  {
    "ptterm": "verde", 
    "dist": 3.8651472724611895, 
    "enterm": "pistachio"
  }, 
  {
    "ptterm": "azul", 
    "dist": 11.202093271216906, 
    "enterm": "umber"
  }, 
  {
    "ptterm": "verde", 
    "dist": 9.674139567108229, 
    "enterm": "umber"
  }, 
  {
    "ptterm": "azul", 
    "dist": 5.497342114495713, 
    "enterm": "grayishblue"
  }, 
  {
    "ptterm": "verde", 
    "dist": 10.873219832306013, 
    "enterm": "grayishblue"
  }, 
  {
    "ptterm": "azul", 
    "dist": 2.9479959915194383, 
    "enterm": "marineblue"
  }, 
  {
    "ptterm": "verde", 
    "dist": 17.148793430081092, 
    "enterm": "marineblue"
  }, 
  {
    "ptterm": "azul", 
    "dist": 2.88195267794411, 
    "enterm": "periwinkleblue"
  }, 
  {
    "ptterm": "verde", 
    "dist": 13.160856798398989, 
    "enterm": "periwinkleblue"
  }, 
  {
    "ptterm": "azul", 
    "dist": 10.995517341634484, 
    "enterm": "greenbrown"
  }, 
  {
    "ptterm": "verde", 
    "dist": 7.134452631151491, 
    "enterm": "greenbrown"
  }, 
  {
    "ptterm": "azul", 
    "dist": 5.804222963956732, 
    "enterm": "darkviolet"
  }, 
  {
    "ptterm": "verde", 
    "dist": 16.34170500847077, 
    "enterm": "darkviolet"
  }, 
  {
    "ptterm": "azul", 
    "dist": 6.688428266377957, 
    "enterm": "purplegray"
  }, 
  {
    "ptterm": "verde", 
    "dist": 10.788471133236216, 
    "enterm": "purplegray"
  }, 
  {
    "ptterm": "azul", 
    "dist": 12.374435167356806, 
    "enterm": "orangebrown"
  }, 
  {
    "ptterm": "verde", 
    "dist": 10.30734842153702, 
    "enterm": "orangebrown"
  }, 
  {
    "ptterm": "azul", 
    "dist": 12.948466229733409, 
    "enterm": "deepred"
  }, 
  {
    "ptterm": "verde", 
    "dist": 13.637434033731322, 
    "enterm": "deepred"
  }, 
  {
    "ptterm": "azul", 
    "dist": 10.174424947542544, 
    "enterm": "salmonpink"
  }, 
  {
    "ptterm": "verde", 
    "dist": 12.188547746060607, 
    "enterm": "salmonpink"
  }, 
  {
    "ptterm": "azul", 
    "dist": 7.094303703996963, 
    "enterm": "slategray"
  }, 
  {
    "ptterm": "verde", 
    "dist": 9.456177456012226, 
    "enterm": "slategray"
  }, 
  {
    "ptterm": "azul", 
    "dist": 8.661606644831549, 
    "enterm": "lightaqua"
  }, 
  {
    "ptterm": "verde", 
    "dist": 6.956985419975415, 
    "enterm": "lightaqua"
  }, 
  {
    "ptterm": "azul", 
    "dist": 3.8580993527941594, 
    "enterm": "royal"
  }, 
  {
    "ptterm": "verde", 
    "dist": 17.94129245396205, 
    "enterm": "royal"
  }, 
  {
    "ptterm": "azul", 
    "dist": 11.599532538706807, 
    "enterm": "burntumber"
  }, 
  {
    "ptterm": "verde", 
    "dist": 10.269798454222384, 
    "enterm": "burntumber"
  }, 
  {
    "ptterm": "azul", 
    "dist": 9.785772021647004, 
    "enterm": "flesh"
  }, 
  {
    "ptterm": "verde", 
    "dist": 9.458634154546633, 
    "enterm": "flesh"
  }, 
  {
    "ptterm": "azul", 
    "dist": 12.228598166154235, 
    "enterm": "mediumgreen"
  }, 
  {
    "ptterm": "verde", 
    "dist": 3.5300123580633236, 
    "enterm": "mediumgreen"
  }, 
  {
    "ptterm": "azul", 
    "dist": 2.9839920815476666, 
    "enterm": "prussianblue"
  }, 
  {
    "ptterm": "verde", 
    "dist": 14.686790475356933, 
    "enterm": "prussianblue"
  }, 
  {
    "ptterm": "azul", 
    "dist": 9.042410171720658, 
    "enterm": "offwhite"
  }, 
  {
    "ptterm": "verde", 
    "dist": 8.03582057120631, 
    "enterm": "offwhite"
  }, 
  {
    "ptterm": "azul", 
    "dist": 8.619361223103304, 
    "enterm": "redpurple"
  }, 
  {
    "ptterm": "verde", 
    "dist": 15.33044061040059, 
    "enterm": "redpurple"
  }, 
  {
    "ptterm": "azul", 
    "dist": 6.8543550083764, 
    "enterm": "darkturquoise"
  }, 
  {
    "ptterm": "verde", 
    "dist": 8.81911227274731, 
    "enterm": "darkturquoise"
  }, 
  {
    "ptterm": "azul", 
    "dist": 8.4550539420492, 
    "enterm": "greengray"
  }, 
  {
    "ptterm": "verde", 
    "dist": 7.756664760956718, 
    "enterm": "greengray"
  }, 
  {
    "ptterm": "azul", 
    "dist": 11.16259093744626, 
    "enterm": "softgreen"
  }, 
  {
    "ptterm": "verde", 
    "dist": 4.249344966566969, 
    "enterm": "softgreen"
  }, 
  {
    "ptterm": "azul", 
    "dist": 7.539593143774973, 
    "enterm": "bubblegumpink"
  }, 
  {
    "ptterm": "verde", 
    "dist": 14.712476048462008, 
    "enterm": "bubblegumpink"
  }, 
  {
    "ptterm": "azul", 
    "dist": 12.627826684014133, 
    "enterm": "copper"
  }, 
  {
    "ptterm": "verde", 
    "dist": 9.720252357384656, 
    "enterm": "copper"
  }, 
  {
    "ptterm": "azul", 
    "dist": 10.969237494087857, 
    "enterm": "jadegreen"
  }, 
  {
    "ptterm": "verde", 
    "dist": 4.383173004711113, 
    "enterm": "jadegreen"
  }, 
  {
    "ptterm": "azul", 
    "dist": 10.201712571906647, 
    "enterm": "deepgreen"
  }, 
  {
    "ptterm": "verde", 
    "dist": 7.705626291998768, 
    "enterm": "deepgreen"
  }, 
  {
    "ptterm": "azul", 
    "dist": 10.281914088699612, 
    "enterm": "skin"
  }, 
  {
    "ptterm": "verde", 
    "dist": 8.720174115254965, 
    "enterm": "skin"
  }, 
  {
    "ptterm": "azul", 
    "dist": 6.907695153067093, 
    "enterm": "aubergine"
  }, 
  {
    "ptterm": "verde", 
    "dist": 14.02110689121791, 
    "enterm": "aubergine"
  }, 
  {
    "ptterm": "azul", 
    "dist": 10.417665382690432, 
    "enterm": "chocolate"
  }, 
  {
    "ptterm": "verde", 
    "dist": 11.1048080743239, 
    "enterm": "chocolate"
  }, 
  {
    "ptterm": "azul", 
    "dist": 7.433899935489018, 
    "enterm": "dullpink"
  }, 
  {
    "ptterm": "verde", 
    "dist": 12.368737909302727, 
    "enterm": "dullpink"
  }, 
  {
    "ptterm": "azul", 
    "dist": 3.899295192063449, 
    "enterm": "dullblue"
  }, 
  {
    "ptterm": "verde", 
    "dist": 12.591797743903667, 
    "enterm": "dullblue"
  }, 
  {
    "ptterm": "azul", 
    "dist": 10.58643739239938, 
    "enterm": "navygreen"
  }, 
  {
    "ptterm": "verde", 
    "dist": 6.628736490760459, 
    "enterm": "navygreen"
  }, 
  {
    "ptterm": "azul", 
    "dist": 8.599656422870389, 
    "enterm": "graybrown"
  }, 
  {
    "ptterm": "verde", 
    "dist": 9.562939491304773, 
    "enterm": "graybrown"
  }, 
  {
    "ptterm": "azul", 
    "dist": 9.661977164860858, 
    "enterm": "nude"
  }, 
  {
    "ptterm": "verde", 
    "dist": 8.90741756432029, 
    "enterm": "nude"
  }, 
  {
    "ptterm": "azul", 
    "dist": 4.011178255101525, 
    "enterm": "denimblue"
  }, 
  {
    "ptterm": "verde", 
    "dist": 13.18571945623445, 
    "enterm": "denimblue"
  }, 
  {
    "ptterm": "azul", 
    "dist": 4.871931276130007, 
    "enterm": "amethyst"
  }, 
  {
    "ptterm": "verde", 
    "dist": 16.437124663655798, 
    "enterm": "amethyst"
  }, 
  {
    "ptterm": "azul", 
    "dist": 10.648304247902578, 
    "enterm": "winered"
  }, 
  {
    "ptterm": "verde", 
    "dist": 12.94310998609015, 
    "enterm": "winered"
  }, 
  {
    "ptterm": "azul", 
    "dist": 13.712864364632035, 
    "enterm": "neon"
  }, 
  {
    "ptterm": "verde", 
    "dist": 2.7132906364655085, 
    "enterm": "neon"
  }, 
  {
    "ptterm": "azul", 
    "dist": 9.485410908178112, 
    "enterm": "eggshell"
  }, 
  {
    "ptterm": "verde", 
    "dist": 7.349701699169622, 
    "enterm": "eggshell"
  }, 
  {
    "ptterm": "azul", 
    "dist": 7.793129101740517, 
    "enterm": "duskypink"
  }, 
  {
    "ptterm": "verde", 
    "dist": 11.685365731134713, 
    "enterm": "duskypink"
  }, 
  {
    "ptterm": "azul", 
    "dist": 9.464932699040146, 
    "enterm": "pine"
  }, 
  {
    "ptterm": "verde", 
    "dist": 7.432194115476962, 
    "enterm": "pine"
  }, 
  {
    "ptterm": "azul", 
    "dist": 12.300152679508802, 
    "enterm": "dirtygreen"
  }, 
  {
    "ptterm": "verde", 
    "dist": 5.014399126374144, 
    "enterm": "dirtygreen"
  }, 
  {
    "ptterm": "azul", 
    "dist": 11.155974687334464, 
    "enterm": "fadedgreen"
  }, 
  {
    "ptterm": "verde", 
    "dist": 4.486159948500732, 
    "enterm": "fadedgreen"
  }, 
  {
    "ptterm": "azul", 
    "dist": 11.168254353038469, 
    "enterm": "brownred"
  }, 
  {
    "ptterm": "verde", 
    "dist": 11.81011918205098, 
    "enterm": "brownred"
  }, 
  {
    "ptterm": "azul", 
    "dist": 10.49869517457104, 
    "enterm": "darktan"
  }, 
  {
    "ptterm": "verde", 
    "dist": 8.754757311043758, 
    "enterm": "darktan"
  }, 
  {
    "ptterm": "azul", 
    "dist": 10.767314760475163, 
    "enterm": "fern"
  }, 
  {
    "ptterm": "verde", 
    "dist": 5.189881210725489, 
    "enterm": "fern"
  }, 
  {
    "ptterm": "azul", 
    "dist": 10.58308519285008, 
    "enterm": "camogreen"
  }, 
  {
    "ptterm": "verde", 
    "dist": 6.696585692492258, 
    "enterm": "camogreen"
  }, 
  {
    "ptterm": "azul", 
    "dist": 8.325514592029942, 
    "enterm": "purplered"
  }, 
  {
    "ptterm": "verde", 
    "dist": 14.331969846791493, 
    "enterm": "purplered"
  }, 
  {
    "ptterm": "azul", 
    "dist": 4.859879525191488, 
    "enterm": "midnight"
  }, 
  {
    "ptterm": "verde", 
    "dist": 14.68293823885518, 
    "enterm": "midnight"
  }, 
  {
    "ptterm": "azul", 
    "dist": 7.501955292436504, 
    "enterm": "reddishpurple"
  }, 
  {
    "ptterm": "verde", 
    "dist": 15.190171221147063, 
    "enterm": "reddishpurple"
  }, 
  {
    "ptterm": "azul", 
    "dist": 12.680803651062378, 
    "enterm": "vomit"
  }, 
  {
    "ptterm": "verde", 
    "dist": 4.740440694181547, 
    "enterm": "vomit"
  }, 
  {
    "ptterm": "azul", 
    "dist": 8.694405520371426, 
    "enterm": "grayishgreen"
  }, 
  {
    "ptterm": "verde", 
    "dist": 7.829155936580641, 
    "enterm": "grayishgreen"
  }, 
  {
    "ptterm": "azul", 
    "dist": 11.467022358246574, 
    "enterm": "swampgreen"
  }, 
  {
    "ptterm": "verde", 
    "dist": 5.460534525308916, 
    "enterm": "swampgreen"
  }, 
  {
    "ptterm": "azul", 
    "dist": 10.344083420052069, 
    "enterm": "burgendy"
  }, 
  {
    "ptterm": "verde", 
    "dist": 12.529925205654276, 
    "enterm": "burgendy"
  }, 
  {
    "ptterm": "azul", 
    "dist": 11.54400377845941, 
    "enterm": "greenishbrown"
  }, 
  {
    "ptterm": "verde", 
    "dist": 7.374833053428156, 
    "enterm": "greenishbrown"
  }, 
  {
    "ptterm": "azul", 
    "dist": 12.112351626109056, 
    "enterm": "puke"
  }, 
  {
    "ptterm": "verde", 
    "dist": 5.592124308344445, 
    "enterm": "puke"
  }, 
  {
    "ptterm": "azul", 
    "dist": 11.651859395827865, 
    "enterm": "auburn"
  }, 
  {
    "ptterm": "verde", 
    "dist": 11.23878065224788, 
    "enterm": "auburn"
  }, 
  {
    "ptterm": "azul", 
    "dist": 9.355166670408467, 
    "enterm": "ivory"
  }, 
  {
    "ptterm": "verde", 
    "dist": 7.232322287215895, 
    "enterm": "ivory"
  }, 
  {
    "ptterm": "azul", 
    "dist": 12.481550906388026, 
    "enterm": "goldenbrown"
  }, 
  {
    "ptterm": "verde", 
    "dist": 8.157613787090161, 
    "enterm": "goldenbrown"
  }, 
  {
    "ptterm": "azul", 
    "dist": 6.799922388191191, 
    "enterm": "electricpurple"
  }, 
  {
    "ptterm": "verde", 
    "dist": 19.387001495766725, 
    "enterm": "electricpurple"
  }, 
  {
    "ptterm": "azul", 
    "dist": 3.932237508292323, 
    "enterm": "perriwinkle"
  }, 
  {
    "ptterm": "verde", 
    "dist": 12.577307295896532, 
    "enterm": "perriwinkle"
  }, 
  {
    "ptterm": "azul", 
    "dist": 8.278178774578013, 
    "enterm": "blushpink"
  }, 
  {
    "ptterm": "verde", 
    "dist": 12.013001755238006, 
    "enterm": "blushpink"
  }, 
  {
    "ptterm": "azul", 
    "dist": 11.367748925038095, 
    "enterm": "oxblood"
  }, 
  {
    "ptterm": "verde", 
    "dist": 12.329516748148707, 
    "enterm": "oxblood"
  }, 
  {
    "ptterm": "azul", 
    "dist": 4.293007783678983, 
    "enterm": "purplishblue"
  }, 
  {
    "ptterm": "verde", 
    "dist": 17.795539347414856, 
    "enterm": "purplishblue"
  }, 
  {
    "ptterm": "azul", 
    "dist": 12.09674547716138, 
    "enterm": "darkyellowgreen"
  }, 
  {
    "ptterm": "verde", 
    "dist": 5.7581850946551025, 
    "enterm": "darkyellowgreen"
  }, 
  {
    "ptterm": "azul", 
    "dist": 10.144726793171994, 
    "enterm": "mutedgreen"
  }, 
  {
    "ptterm": "verde", 
    "dist": 5.6661611134351295, 
    "enterm": "mutedgreen"
  }, 
  {
    "ptterm": "azul", 
    "dist": 9.057084153032285, 
    "enterm": "darkmaroon"
  }, 
  {
    "ptterm": "verde", 
    "dist": 12.926039651344137, 
    "enterm": "darkmaroon"
  }, 
  {
    "ptterm": "azul", 
    "dist": 12.305125991375654, 
    "enterm": "caramel"
  }, 
  {
    "ptterm": "verde", 
    "dist": 8.382041504400968, 
    "enterm": "caramel"
  }, 
  {
    "ptterm": "azul", 
    "dist": 10.848334929678623, 
    "enterm": "olivedrab"
  }, 
  {
    "ptterm": "verde", 
    "dist": 6.719145275883054, 
    "enterm": "olivedrab"
  }, 
  {
    "ptterm": "azul", 
    "dist": 11.83124913978425, 
    "enterm": "treegreen"
  }, 
  {
    "ptterm": "verde", 
    "dist": 4.538610834782006, 
    "enterm": "treegreen"
  }, 
  {
    "ptterm": "azul", 
    "dist": 11.752895977713045, 
    "enterm": "asparagus"
  }, 
  {
    "ptterm": "verde", 
    "dist": 5.017195360314745, 
    "enterm": "asparagus"
  }
]